show_your_work/__init__.py
show_your_work_utils-0.3.0.dist-info/METADATA
show_your_work_utils-0.3.0.dist-info/WHEEL
show_your_work_utils-0.3.0.dist-info/RECORD
