Metadata-Version: 2.4
Name: show-your-work-utils
Version: 0.3.0
Summary: Add your description here
Author-email: CD Clark III <clifton.clark@gmail.com>
Requires-Python: >=3.12
Requires-Dist: antlr4-python3-runtime==4.11
Requires-Dist: latexify-py>=0.4.4
Requires-Dist: pint>=0.24.4
Requires-Dist: pyparsing>=3.2.3
Requires-Dist: sympy>=1.14.0
